[{"content":"This is my first post\n","permalink":"https://Sulstrong.github.io/zh/hobby/sample/","summary":"This is my first post","title":"hobby post"},{"content":"This is my first post\n","permalink":"https://Sulstrong.github.io/zh/posts/sample/","summary":"This is my first post","title":"This is my first formal post"},{"content":"This is my first post\n","permalink":"https://Sulstrong.github.io/zh/project/sample/","summary":"This is my first post","title":"This is my first formal post"},{"content":"\rSulv\u0026#39;s Blog\r一个记录技术,阅读，生活的博客\rBaidu\rBaidu\r","permalink":"https://Sulstrong.github.io/zh/links/","summary":"Sulv\u0026#39;s Blog 一个记录技术,阅读，生活的博客 Baidu Baidu","title":"友情链接"},{"content":"","permalink":"https://Sulstrong.github.io/zh/project/test-projects/","summary":"","title":"Experience"},{"content":"广西桂林人\n现在居住在Jersey City\n两只猫\n丸子 和 Momo\nbody { font-family: \u0026#39;Code New Roman\u0026#39;, sans-serif; font-size: 1rem; line-height: 1.5; margin: 0; } .post-content pre code { display: block; margin: auto 0; padding: 10px; /* 主要代码颜色 */ color: #abb2bf; font-weight: 200; overflow-x: auto; word-break: break-all; /* 关键字 */ .hljs-keyword, .hljs-selector-tag, .hljs-literal, .hljs-link, .hljs-meta, .hljs-type { font-weight: 200; color: #c678dd; }``` \u0026lt;!doctype html\u0026gt; Test ","permalink":"https://Sulstrong.github.io/zh/about/","summary":"广西桂林人 现在居住在Jersey City 两只猫 丸子 和 Momo body { font-family: \u0026#39;Code New Roman\u0026#39;, sans-serif; font-size: 1rem; line-height: 1.5; margin: 0; } .post-content pre code { display: block; margin: auto 0; padding: 10px; /* 主要代码颜色 */ color: #abb2bf; font-weight: 200; overflow-x: auto; word-break: break-all; /* 关键字 */","title":"关于我"},{"content":"This is my resume\n","permalink":"https://Sulstrong.github.io/zh/resume/","summary":"This is my resume","title":"简历"},{"content":"Hello World 我的生活多姿多彩\n","permalink":"https://Sulstrong.github.io/zh/life/life/","summary":"Hello World 我的生活多姿多彩","title":"Life"},{"content":"","permalink":"https://Sulstrong.github.io/zh/read/read/","summary":"","title":"Read"},{"content":"","permalink":"https://Sulstrong.github.io/zh/posts/tech/","summary":"","title":"Tech"}]